setup.cfg
setup.py
segment_source/__init__.py
segment_source/client.py
segment_source/domain_pb2.py
segment_source/domain_pb2_grpc.py
segment_source/lsp.py
segment_source/stats.py
segment_source.egg-info/PKG-INFO
segment_source.egg-info/SOURCES.txt
segment_source.egg-info/dependency_links.txt
segment_source.egg-info/requires.txt
segment_source.egg-info/top_level.txt