Metadata-Version: 1.0
Name: segment-source
Version: 0.10.1
Summary: Python source client
Home-page: https://github.com/segmentio/python-source
Author: Segment
Author-email: friends@segment.com
License: UNKNOWN
Platform: UNKNOWN
